pyassemblyai
