Metadata-Version: 1.0
Name: pyassemblyai
Version: 0.2.0
Summary: unofficial python api for assemblyai.com
Home-page: https://github.com/JarbasAl/pyassemblyai
Author: jarbasai
Author-email: jarbasai@mailfence.com
License: MIT
Platform: UNKNOWN
